LICENSE
MANIFEST.in
README.rst
setup.py
django_atomic_signals/__init__.py
django_atomic_signals.egg-info/PKG-INFO
django_atomic_signals.egg-info/SOURCES.txt
django_atomic_signals.egg-info/dependency_links.txt
django_atomic_signals.egg-info/top_level.txt
django_atomic_signals.egg-info/zip-safe