Metadata-Version: 1.1
Name: django-atomic-signals
Version: 2.0.0
Summary: Signals for atomic transaction blocks in Django 1.6+
Home-page: https://github.com/adamchainz/django_atomic_signals
Author: Adam Johnson
Author-email: me@adamj.eu
License: Copyright (c) Nick Bruun <nick@bruun.co>
